geolocation_pkg/__init__.py
geolocation_pkg/geolocation.py
geolocation_utils_shwemoethantx24170399-0.1.0.dist-info/licenses/LICENSE
geolocation_utils_shwemoethantx24170399-0.1.0.dist-info/METADATA
geolocation_utils_shwemoethantx24170399-0.1.0.dist-info/WHEEL
geolocation_utils_shwemoethantx24170399-0.1.0.dist-info/top_level.txt
geolocation_utils_shwemoethantx24170399-0.1.0.dist-info/RECORD
