Metadata-Version: 2.4
Name: geolocation-utils-shwemoethantx24170399
Version: 0.1.0
Summary: Simple geolocation utilities for distance and proximity calculations
Home-page: https://github.com/ShweMoeThantAurum/geolocation-utils
Author: Shwe Moe Thant
Author-email: shwemoethant04@gmail.com
Classifier: Programming Language :: Python :: 3
Classifier: License :: OSI Approved :: MIT License
Classifier: Operating System :: OS Independent
Requires-Python: >=3.6
License-File: LICENSE
Dynamic: author
Dynamic: author-email
Dynamic: classifier
Dynamic: description-content-type
Dynamic: home-page
Dynamic: license-file
Dynamic: requires-python
Dynamic: summary
